structlog_ext_utils/__init__.py
structlog_ext_utils/__version__.py
structlog_ext_utils/processors.py
structlog_ext_utils-0.1.0a5.dist-info/LICENSE
structlog_ext_utils-0.1.0a5.dist-info/METADATA
structlog_ext_utils-0.1.0a5.dist-info/WHEEL
structlog_ext_utils-0.1.0a5.dist-info/top_level.txt
structlog_ext_utils-0.1.0a5.dist-info/RECORD
