Metadata-Version: 2.1
Name: structlog-ext-utils
Version: 0.1.0a5
Summary: structlog extension utilities
Home-page: https://github.com/amenezes/structlog_ext_utils
Author: alexandre menezes
Author-email: alexandre.fmenezes@gmail.com
License: Apache-2.0
Project-URL: Documentation, https://structlog_ext_utils.amenezes.net
Project-URL: Code, https://github.com/amenezes/structlog_ext_utils
Project-URL: Issue tracker, https://github.com/amenezes/structlog_ext_utils/issues
Platform: UNKNOWN
Classifier: Intended Audience :: Developers
Classifier: License :: OSI Approved :: Apache Software License
Classifier: Operating System :: OS Independent
Classifier: Programming Language :: Python :: 3 :: Only
Classifier: Programming Language :: Python :: 3.6
Classifier: Programming Language :: Python :: 3.7
Classifier: Programming Language :: Python :: 3.8
Classifier: Programming Language :: Python :: 3.9
Classifier: Programming Language :: Python :: Implementation :: CPython
Classifier: Programming Language :: Python :: Implementation :: PyPy
Classifier: Topic :: Software Development :: Libraries
Requires-Python: >=3.6.0
Requires-Dist: structlog (<=20.1.0)
Requires-Dist: python-json-logger
Requires-Dist: pendulum
Provides-Extra: all
Requires-Dist: structlog (<=20.1.0) ; extra == 'all'
Requires-Dist: python-json-logger ; extra == 'all'
Requires-Dist: portray ; extra == 'all'
Provides-Extra: docs
Requires-Dist: portray ; extra == 'docs'
